msglink/__init__.py
msglink/packets.py
msglink/protocol.py
msglink/py.typed
msglink/router.py
msglink-1.5.7.dist-info/LICENSE.txt
msglink-1.5.7.dist-info/METADATA
msglink-1.5.7.dist-info/WHEEL
msglink-1.5.7.dist-info/top_level.txt
msglink-1.5.7.dist-info/RECORD
