Metadata-Version: 2.1
Name: msglink
Version: 1.5.7
Summary: msglink client library
Home-page: 
Author: Robert Brünig
Author-email: 
License: LGPL v3
License-File: LICENSE.txt
